LICENSE
setup.py
tanshicheng/__init__.py
tanshicheng/aa_parameter_file.py
tanshicheng/ab_progress_and_time.py
tanshicheng/ac_public_process.py
tanshicheng/ae_draw.py
tanshicheng/af_taskdb_api.py
tanshicheng.egg-info/PKG-INFO
tanshicheng.egg-info/SOURCES.txt
tanshicheng.egg-info/dependency_links.txt
tanshicheng.egg-info/requires.txt
tanshicheng.egg-info/top_level.txt