Metadata-Version: 2.1
Name: tanshicheng
Version: 0.3.24
Summary: tanshicheng's tools
Home-page: https://github.com/aitsc
Author: tanshicheng
License: GPLv3
Keywords: tools
Platform: UNKNOWN
Classifier: Intended Audience :: Developers
Classifier: License :: OSI Approved :: GNU General Public License v3 (GPLv3)
Classifier: Operating System :: MacOS
Classifier: Programming Language :: Python :: 3 :: Only
Classifier: Topic :: Software Development :: Libraries
Requires-Python: >=3.6
License-File: LICENSE
